bgp_data_interface/__init__.py
bgp_data_interface/amr.py
bgp_data_interface/fusion_solar.py
bgp_data_interface/openmeteo.py
bgp_data_interface/pi.py
bgp_data_interface/py.typed
bgp_data_interface/s3_energy.py
bgp_data_interface/s3_weather.py
bgp_data_interface/tmd.py
bgp_data_interface/weather_api.py
bgp_data_interface/wu.py
bgp_data_interface/amr_api/amr_g3.py
bgp_data_interface/amr_api/amr_pw.py
bgp_data_interface/amr_api/smartview.py
bgp_data_interface/fusion_solar_api/FusionSolarAPI.py
bgp_data_interface/fusion_solar_api/__init__.py
bgp_data_interface/fusion_solar_api/sg5_scraping.py
bgp_data_interface/openmeteo_api/OpenmeteoApi.py
bgp_data_interface/openmeteo_api/__init__.py
bgp_data_interface/pi_api/BBO_tag_webids.csv
bgp_data_interface/pi_api/BTW_tag_webids.csv
bgp_data_interface/pi_api/_.bgrimmpower.crt
bgp_data_interface/pi_api/__init__.py
bgp_data_interface/pi_api/bangbo.py
bgp_data_interface/pi_api/bothong.py
bgp_data_interface/pi_api/pi_api.py
bgp_data_interface/s3_bucket/S3Energy.py
bgp_data_interface/s3_bucket/S3Weather.py
bgp_data_interface/tmd_api/TMD_API.py
bgp_data_interface/tmd_api/__init__.py
bgp_data_interface/utils/location.py
bgp_data_interface/utils/save_csv.py
bgp_data_interface/utils/source.py
bgp_data_interface/utils/type.py
bgp_data_interface/weather_api_api/WeatherAPI.py
bgp_data_interface/weather_api_api/__init__.py
bgp_data_interface/wu_api/WeatherUndergroundAPI.py
bgp_data_interface-0.9.2.dist-info/METADATA
bgp_data_interface-0.9.2.dist-info/WHEEL
bgp_data_interface-0.9.2.dist-info/licenses/LICENSE.txt
bgp_data_interface-0.9.2.dist-info/RECORD
